[
  {
    "variant_id": "V-IPH15-BL-128",
    "location_id": "WH-HK",
    "on_hand": 25,
    "reserved": 0,
    "available": 25,
    "updated_at": "2025-10-06T10:11:54.646685Z"
  },
  {
    "variant_id": "V-IPH15-BL-128",
    "location_id": "STO-CWB",
    "on_hand": 13,
    "reserved": 7,
    "available": 6,
    "updated_at": "2025-10-06T10:11:54.646703Z"
  },
  {
    "variant_id": "V-IPH15-BL-128",
    "location_id": "STO-TST",
    "on_hand": 14,
    "reserved": 5,
    "available": 9,
    "updated_at": "2025-10-06T10:11:54.646711Z"
  },
  {
    "variant_id": "V-IPH15-BL-256",
    "location_id": "WH-HK",
    "on_hand": 24,
    "reserved": 3,
    "available": 21,
    "updated_at": "2025-10-06T10:11:54.646718Z"
  },
  {
    "variant_id": "V-IPH15-BL-256",
    "location_id": "STO-CWB",
    "on_hand": 12,
    "reserved": 4,
    "available": 8,
    "updated_at": "2025-10-06T10:11:54.646725Z"
  },
  {
    "variant_id": "V-IPH15-BL-256",
    "location_id": "STO-TST",
    "on_hand": 3,
    "reserved": 2,
    "available": 1,
    "updated_at": "2025-10-06T10:11:54.646732Z"
  },
  {
    "variant_id": "V-IPH15-BL-512",
    "location_id": "WH-HK",
    "on_hand": 6,
    "reserved": 1,
    "available": 5,
    "updated_at": "2025-10-06T10:11:54.646742Z"
  },
  {
    "variant_id": "V-IPH15-BL-512",
    "location_id": "STO-CWB",
    "on_hand": 15,
    "reserved": 3,
    "available": 12,
    "updated_at": "2025-10-06T10:11:54.646751Z"
  },
  {
    "variant_id": "V-IPH15-BL-512",
    "location_id": "STO-TST",
    "on_hand": 4,
    "reserved": 2,
    "available": 2,
    "updated_at": "2025-10-06T10:11:54.646758Z"
  },
  {
    "variant_id": "V-IPH15-BL-128",
    "location_id": "WH-HK",
    "on_hand": 2,
    "reserved": 2,
    "available": 0,
    "updated_at": "2025-10-06T10:11:54.646767Z"
  },
  {
    "variant_id": "V-IPH15-BL-128",
    "location_id": "STO-CWB",
    "on_hand": 11,
    "reserved": 0,
    "available": 11,
    "updated_at": "2025-10-06T10:11:54.646774Z"
  },
  {
    "variant_id": "V-IPH15-BL-128",
    "location_id": "STO-TST",
    "on_hand": 22,
    "reserved": 7,
    "available": 15,
    "updated_at": "2025-10-06T10:11:54.646781Z"
  },
  {
    "variant_id": "V-IPH15-BL-256",
    "location_id": "WH-HK",
    "on_hand": 22,
    "reserved": 6,
    "available": 16,
    "updated_at": "2025-10-06T10:11:54.646788Z"
  },
  {
    "variant_id": "V-IPH15-BL-256",
    "location_id": "STO-CWB",
    "on_hand": 14,
    "reserved": 5,
    "available": 9,
    "updated_at": "2025-10-06T10:11:54.646795Z"
  },
  {
    "variant_id": "V-IPH15-BL-256",
    "location_id": "STO-TST",
    "on_hand": 11,
    "reserved": 1,
    "available": 10,
    "updated_at": "2025-10-06T10:11:54.646802Z"
  },
  {
    "variant_id": "V-IPH15-BL-512",
    "location_id": "WH-HK",
    "on_hand": 9,
    "reserved": 5,
    "available": 4,
    "updated_at": "2025-10-06T10:11:54.646810Z"
  },
  {
    "variant_id": "V-IPH15-BL-512",
    "location_id": "STO-CWB",
    "on_hand": 9,
    "reserved": 1,
    "available": 8,
    "updated_at": "2025-10-06T10:11:54.646816Z"
  },
  {
    "variant_id": "V-IPH15-BL-512",
    "location_id": "STO-TST",
    "on_hand": 7,
    "reserved": 4,
    "available": 3,
    "updated_at": "2025-10-06T10:11:54.646821Z"
  },
  {
    "variant_id": "V-IPH15-GR-128",
    "location_id": "WH-HK",
    "on_hand": 1,
    "reserved": 1,
    "available": 0,
    "updated_at": "2025-10-06T10:11:54.646825Z"
  },
  {
    "variant_id": "V-IPH15-GR-128",
    "location_id": "STO-CWB",
    "on_hand": 25,
    "reserved": 5,
    "available": 20,
    "updated_at": "2025-10-06T10:11:54.646829Z"
  },
  {
    "variant_id": "V-IPH15-GR-128",
    "location_id": "STO-TST",
    "on_hand": 24,
    "reserved": 5,
    "available": 19,
    "updated_at": "2025-10-06T10:11:54.646833Z"
  },
  {
    "variant_id": "V-IPH15-GR-256",
    "location_id": "WH-HK",
    "on_hand": 1,
    "reserved": 1,
    "available": 0,
    "updated_at": "2025-10-06T10:11:54.646836Z"
  },
  {
    "variant_id": "V-IPH15-GR-256",
    "location_id": "STO-CWB",
    "on_hand": 25,
    "reserved": 1,
    "available": 24,
    "updated_at": "2025-10-06T10:11:54.646841Z"
  },
  {
    "variant_id": "V-IPH15-GR-256",
    "location_id": "STO-TST",
    "on_hand": 0,
    "reserved": 0,
    "available": 0,
    "updated_at": "2025-10-06T10:11:54.646845Z"
  },
  {
    "variant_id": "V-IPH15-GR-512",
    "location_id": "WH-HK",
    "on_hand": 4,
    "reserved": 3,
    "available": 1,
    "updated_at": "2025-10-06T10:11:54.646849Z"
  },
  {
    "variant_id": "V-IPH15-GR-512",
    "location_id": "STO-CWB",
    "on_hand": 16,
    "reserved": 8,
    "available": 8,
    "updated_at": "2025-10-06T10:11:54.646853Z"
  },
  {
    "variant_id": "V-IPH15-GR-512",
    "location_id": "STO-TST",
    "on_hand": 22,
    "reserved": 0,
    "available": 22,
    "updated_at": "2025-10-06T10:11:54.646856Z"
  },
  {
    "variant_id": "V-IPH15-PI-128",
    "location_id": "WH-HK",
    "on_hand": 6,
    "reserved": 1,
    "available": 5,
    "updated_at": "2025-10-06T10:11:54.646860Z"
  },
  {
    "variant_id": "V-IPH15-PI-128",
    "location_id": "STO-CWB",
    "on_hand": 23,
    "reserved": 4,
    "available": 19,
    "updated_at": "2025-10-06T10:11:54.646864Z"
  },
  {
    "variant_id": "V-IPH15-PI-128",
    "location_id": "STO-TST",
    "on_hand": 22,
    "reserved": 6,
    "available": 16,
    "updated_at": "2025-10-06T10:11:54.646868Z"
  },
  {
    "variant_id": "V-IPH15-PI-256",
    "location_id": "WH-HK",
    "on_hand": 22,
    "reserved": 5,
    "available": 17,
    "updated_at": "2025-10-06T10:11:54.646872Z"
  },
  {
    "variant_id": "V-IPH15-PI-256",
    "location_id": "STO-CWB",
    "on_hand": 10,
    "reserved": 0,
    "available": 10,
    "updated_at": "2025-10-06T10:11:54.646876Z"
  },
  {
    "variant_id": "V-IPH15-PI-256",
    "location_id": "STO-TST",
    "on_hand": 7,
    "reserved": 6,
    "available": 1,
    "updated_at": "2025-10-06T10:11:54.646880Z"
  },
  {
    "variant_id": "V-IPH15-PI-512",
    "location_id": "WH-HK",
    "on_hand": 0,
    "reserved": 0,
    "available": 0,
    "updated_at": "2025-10-06T10:11:54.646884Z"
  },
  {
    "variant_id": "V-IPH15-PI-512",
    "location_id": "STO-CWB",
    "on_hand": 1,
    "reserved": 1,
    "available": 0,
    "updated_at": "2025-10-06T10:11:54.646888Z"
  },
  {
    "variant_id": "V-IPH15-PI-512",
    "location_id": "STO-TST",
    "on_hand": 11,
    "reserved": 2,
    "available": 9,
    "updated_at": "2025-10-06T10:11:54.646892Z"
  },
  {
    "variant_id": "V-IPH15-YE-128",
    "location_id": "WH-HK",
    "on_hand": 19,
    "reserved": 7,
    "available": 12,
    "updated_at": "2025-10-06T10:11:54.646895Z"
  },
  {
    "variant_id": "V-IPH15-YE-128",
    "location_id": "STO-CWB",
    "on_hand": 2,
    "reserved": 0,
    "available": 2,
    "updated_at": "2025-10-06T10:11:54.646899Z"
  },
  {
    "variant_id": "V-IPH15-YE-128",
    "location_id": "STO-TST",
    "on_hand": 10,
    "reserved": 3,
    "available": 7,
    "updated_at": "2025-10-06T10:11:54.646902Z"
  },
  {
    "variant_id": "V-IPH15-YE-256",
    "location_id": "WH-HK",
    "on_hand": 13,
    "reserved": 1,
    "available": 12,
    "updated_at": "2025-10-06T10:11:54.646906Z"
  },
  {
    "variant_id": "V-IPH15-YE-256",
    "location_id": "STO-CWB",
    "on_hand": 2,
    "reserved": 0,
    "available": 2,
    "updated_at": "2025-10-06T10:11:54.646909Z"
  },
  {
    "variant_id": "V-IPH15-YE-256",
    "location_id": "STO-TST",
    "on_hand": 11,
    "reserved": 5,
    "available": 6,
    "updated_at": "2025-10-06T10:11:54.646913Z"
  },
  {
    "variant_id": "V-IPH15-YE-512",
    "location_id": "WH-HK",
    "on_hand": 10,
    "reserved": 6,
    "available": 4,
    "updated_at": "2025-10-06T10:11:54.646917Z"
  },
  {
    "variant_id": "V-IPH15-YE-512",
    "location_id": "STO-CWB",
    "on_hand": 7,
    "reserved": 5,
    "available": 2,
    "updated_at": "2025-10-06T10:11:54.646921Z"
  },
  {
    "variant_id": "V-IPH15-YE-512",
    "location_id": "STO-TST",
    "on_hand": 20,
    "reserved": 2,
    "available": 18,
    "updated_at": "2025-10-06T10:11:54.646924Z"
  },
  {
    "variant_id": "V-IPH15PRO-NA-128",
    "location_id": "WH-HK",
    "on_hand": 11,
    "reserved": 7,
    "available": 4,
    "updated_at": "2025-10-06T10:11:54.646928Z"
  },
  {
    "variant_id": "V-IPH15PRO-NA-128",
    "location_id": "STO-CWB",
    "on_hand": 21,
    "reserved": 1,
    "available": 20,
    "updated_at": "2025-10-06T10:11:54.646932Z"
  },
  {
    "variant_id": "V-IPH15PRO-NA-128",
    "location_id": "STO-TST",
    "on_hand": 3,
    "reserved": 0,
    "available": 3,
    "updated_at": "2025-10-06T10:11:54.646935Z"
  },
  {
    "variant_id": "V-IPH15PRO-NA-256",
    "location_id": "WH-HK",
    "on_hand": 12,
    "reserved": 5,
    "available": 7,
    "updated_at": "2025-10-06T10:11:54.646939Z"
  },
  {
    "variant_id": "V-IPH15PRO-NA-256",
    "location_id": "STO-CWB",
    "on_hand": 16,
    "reserved": 6,
    "available": 10,
    "updated_at": "2025-10-06T10:11:54.646943Z"
  },
  {
    "variant_id": "V-IPH15PRO-NA-256",
    "location_id": "STO-TST",
    "on_hand": 10,
    "reserved": 3,
    "available": 7,
    "updated_at": "2025-10-06T10:11:54.646947Z"
  },
  {
    "variant_id": "V-IPH15PRO-NA-512",
    "location_id": "WH-HK",
    "on_hand": 21,
    "reserved": 7,
    "available": 14,
    "updated_at": "2025-10-06T10:11:54.646950Z"
  },
  {
    "variant_id": "V-IPH15PRO-NA-512",
    "location_id": "STO-CWB",
    "on_hand": 4,
    "reserved": 1,
    "available": 3,
    "updated_at": "2025-10-06T10:11:54.646954Z"
  },
  {
    "variant_id": "V-IPH15PRO-NA-512",
    "location_id": "STO-TST",
    "on_hand": 14,
    "reserved": 8,
    "available": 6,
    "updated_at": "2025-10-06T10:11:54.646958Z"
  },
  {
    "variant_id": "V-IPH15PRO-NA-1024",
    "location_id": "WH-HK",
    "on_hand": 22,
    "reserved": 3,
    "available": 19,
    "updated_at": "2025-10-06T10:11:54.646962Z"
  },
  {
    "variant_id": "V-IPH15PRO-NA-1024",
    "location_id": "STO-CWB",
    "on_hand": 21,
    "reserved": 4,
    "available": 17,
    "updated_at": "2025-10-06T10:11:54.646965Z"
  },
  {
    "variant_id": "V-IPH15PRO-NA-1024",
    "location_id": "STO-TST",
    "on_hand": 25,
    "reserved": 5,
    "available": 20,
    "updated_at": "2025-10-06T10:11:54.646969Z"
  },
  {
    "variant_id": "V-IPH15PRO-BL-128",
    "location_id": "WH-HK",
    "on_hand": 3,
    "reserved": 3,
    "available": 0,
    "updated_at": "2025-10-06T10:11:54.646972Z"
  },
  {
    "variant_id": "V-IPH15PRO-BL-128",
    "location_id": "STO-CWB",
    "on_hand": 6,
    "reserved": 5,
    "available": 1,
    "updated_at": "2025-10-06T10:11:54.646979Z"
  },
  {
    "variant_id": "V-IPH15PRO-BL-128",
    "location_id": "STO-TST",
    "on_hand": 17,
    "reserved": 6,
    "available": 11,
    "updated_at": "2025-10-06T10:11:54.646983Z"
  },
  {
    "variant_id": "V-IPH15PRO-BL-256",
    "location_id": "WH-HK",
    "on_hand": 22,
    "reserved": 3,
    "available": 19,
    "updated_at": "2025-10-06T10:11:54.646991Z"
  },
  {
    "variant_id": "V-IPH15PRO-BL-256",
    "location_id": "STO-CWB",
    "on_hand": 19,
    "reserved": 2,
    "available": 17,
    "updated_at": "2025-10-06T10:11:54.646995Z"
  },
  {
    "variant_id": "V-IPH15PRO-BL-256",
    "location_id": "STO-TST",
    "on_hand": 10,
    "reserved": 1,
    "available": 9,
    "updated_at": "2025-10-06T10:11:54.646999Z"
  },
  {
    "variant_id": "V-IPH15PRO-BL-512",
    "location_id": "WH-HK",
    "on_hand": 1,
    "reserved": 0,
    "available": 1,
    "updated_at": "2025-10-06T10:11:54.647003Z"
  },
  {
    "variant_id": "V-IPH15PRO-BL-512",
    "location_id": "STO-CWB",
    "on_hand": 14,
    "reserved": 5,
    "available": 9,
    "updated_at": "2025-10-06T10:11:54.647007Z"
  },
  {
    "variant_id": "V-IPH15PRO-BL-512",
    "location_id": "STO-TST",
    "on_hand": 2,
    "reserved": 2,
    "available": 0,
    "updated_at": "2025-10-06T10:11:54.647011Z"
  },
  {
    "variant_id": "V-IPH15PRO-BL-1024",
    "location_id": "WH-HK",
    "on_hand": 23,
    "reserved": 6,
    "available": 17,
    "updated_at": "2025-10-06T10:11:54.647015Z"
  },
  {
    "variant_id": "V-IPH15PRO-BL-1024",
    "location_id": "STO-CWB",
    "on_hand": 0,
    "reserved": 0,
    "available": 0,
    "updated_at": "2025-10-06T10:11:54.647019Z"
  },
  {
    "variant_id": "V-IPH15PRO-BL-1024",
    "location_id": "STO-TST",
    "on_hand": 23,
    "reserved": 7,
    "available": 16,
    "updated_at": "2025-10-06T10:11:54.647023Z"
  },
  {
    "variant_id": "V-IPH15PRO-WH-128",
    "location_id": "WH-HK",
    "on_hand": 4,
    "reserved": 2,
    "available": 2,
    "updated_at": "2025-10-06T10:11:54.647026Z"
  },
  {
    "variant_id": "V-IPH15PRO-WH-128",
    "location_id": "STO-CWB",
    "on_hand": 12,
    "reserved": 2,
    "available": 10,
    "updated_at": "2025-10-06T10:11:54.647030Z"
  },
  {
    "variant_id": "V-IPH15PRO-WH-128",
    "location_id": "STO-TST",
    "on_hand": 13,
    "reserved": 7,
    "available": 6,
    "updated_at": "2025-10-06T10:11:54.647034Z"
  },
  {
    "variant_id": "V-IPH15PRO-WH-256",
    "location_id": "WH-HK",
    "on_hand": 24,
    "reserved": 3,
    "available": 21,
    "updated_at": "2025-10-06T10:11:54.647037Z"
  },
  {
    "variant_id": "V-IPH15PRO-WH-256",
    "location_id": "STO-CWB",
    "on_hand": 14,
    "reserved": 1,
    "available": 13,
    "updated_at": "2025-10-06T10:11:54.647041Z"
  },
  {
    "variant_id": "V-IPH15PRO-WH-256",
    "location_id": "STO-TST",
    "on_hand": 11,
    "reserved": 2,
    "available": 9,
    "updated_at": "2025-10-06T10:11:54.647044Z"
  },
  {
    "variant_id": "V-IPH15PRO-WH-512",
    "location_id": "WH-HK",
    "on_hand": 11,
    "reserved": 6,
    "available": 5,
    "updated_at": "2025-10-06T10:11:54.647048Z"
  },
  {
    "variant_id": "V-IPH15PRO-WH-512",
    "location_id": "STO-CWB",
    "on_hand": 15,
    "reserved": 4,
    "available": 11,
    "updated_at": "2025-10-06T10:11:54.647051Z"
  },
  {
    "variant_id": "V-IPH15PRO-WH-512",
    "location_id": "STO-TST",
    "on_hand": 25,
    "reserved": 5,
    "available": 20,
    "updated_at": "2025-10-06T10:11:54.647055Z"
  },
  {
    "variant_id": "V-IPH15PRO-WH-1024",
    "location_id": "WH-HK",
    "on_hand": 5,
    "reserved": 3,
    "available": 2,
    "updated_at": "2025-10-06T10:11:54.647059Z"
  },
  {
    "variant_id": "V-IPH15PRO-WH-1024",
    "location_id": "STO-CWB",
    "on_hand": 0,
    "reserved": 0,
    "available": 0,
    "updated_at": "2025-10-06T10:11:54.647063Z"
  },
  {
    "variant_id": "V-IPH15PRO-WH-1024",
    "location_id": "STO-TST",
    "on_hand": 3,
    "reserved": 3,
    "available": 0,
    "updated_at": "2025-10-06T10:11:54.647066Z"
  },
  {
    "variant_id": "V-IPH15PRO-BL-128",
    "location_id": "WH-HK",
    "on_hand": 14,
    "reserved": 6,
    "available": 8,
    "updated_at": "2025-10-06T10:11:54.647070Z"
  },
  {
    "variant_id": "V-IPH15PRO-BL-128",
    "location_id": "STO-CWB",
    "on_hand": 2,
    "reserved": 1,
    "available": 1,
    "updated_at": "2025-10-06T10:11:54.647074Z"
  },
  {
    "variant_id": "V-IPH15PRO-BL-128",
    "location_id": "STO-TST",
    "on_hand": 25,
    "reserved": 4,
    "available": 21,
    "updated_at": "2025-10-06T10:11:54.647077Z"
  },
  {
    "variant_id": "V-IPH15PRO-BL-256",
    "location_id": "WH-HK",
    "on_hand": 1,
    "reserved": 1,
    "available": 0,
    "updated_at": "2025-10-06T10:11:54.647081Z"
  },
  {
    "variant_id": "V-IPH15PRO-BL-256",
    "location_id": "STO-CWB",
    "on_hand": 19,
    "reserved": 0,
    "available": 19,
    "updated_at": "2025-10-06T10:11:54.647085Z"
  },
  {
    "variant_id": "V-IPH15PRO-BL-256",
    "location_id": "STO-TST",
    "on_hand": 9,
    "reserved": 8,
    "available": 1,
    "updated_at": "2025-10-06T10:11:54.647089Z"
  },
  {
    "variant_id": "V-IPH15PRO-BL-512",
    "location_id": "WH-HK",
    "on_hand": 1,
    "reserved": 1,
    "available": 0,
    "updated_at": "2025-10-06T10:11:54.647093Z"
  },
  {
    "variant_id": "V-IPH15PRO-BL-512",
    "location_id": "STO-CWB",
    "on_hand": 14,
    "reserved": 2,
    "available": 12,
    "updated_at": "2025-10-06T10:11:54.647096Z"
  },
  {
    "variant_id": "V-IPH15PRO-BL-512",
    "location_id": "STO-TST",
    "on_hand": 4,
    "reserved": 2,
    "available": 2,
    "updated_at": "2025-10-06T10:11:54.647100Z"
  },
  {
    "variant_id": "V-IPH15PRO-BL-1024",
    "location_id": "WH-HK",
    "on_hand": 7,
    "reserved": 0,
    "available": 7,
    "updated_at": "2025-10-06T10:11:54.647103Z"
  },
  {
    "variant_id": "V-IPH15PRO-BL-1024",
    "location_id": "STO-CWB",
    "on_hand": 8,
    "reserved": 3,
    "available": 5,
    "updated_at": "2025-10-06T10:11:54.647107Z"
  },
  {
    "variant_id": "V-IPH15PRO-BL-1024",
    "location_id": "STO-TST",
    "on_hand": 22,
    "reserved": 2,
    "available": 20,
    "updated_at": "2025-10-06T10:11:54.647110Z"
  },
  {
    "variant_id": "V-IPAD-AIRM2-11-BL-128",
    "location_id": "WH-HK",
    "on_hand": 7,
    "reserved": 2,
    "available": 5,
    "updated_at": "2025-10-06T10:11:54.647114Z"
  },
  {
    "variant_id": "V-IPAD-AIRM2-11-BL-128",
    "location_id": "STO-CWB",
    "on_hand": 5,
    "reserved": 0,
    "available": 5,
    "updated_at": "2025-10-06T10:11:54.647118Z"
  },
  {
    "variant_id": "V-IPAD-AIRM2-11-BL-128",
    "location_id": "STO-TST",
    "on_hand": 14,
    "reserved": 8,
    "available": 6,
    "updated_at": "2025-10-06T10:11:54.647121Z"
  },
  {
    "variant_id": "V-IPAD-AIRM2-11-BL-256",
    "location_id": "WH-HK",
    "on_hand": 16,
    "reserved": 1,
    "available": 15,
    "updated_at": "2025-10-06T10:11:54.647125Z"
  },
  {
    "variant_id": "V-IPAD-AIRM2-11-BL-256",
    "location_id": "STO-CWB",
    "on_hand": 6,
    "reserved": 4,
    "available": 2,
    "updated_at": "2025-10-06T10:11:54.647128Z"
  },
  {
    "variant_id": "V-IPAD-AIRM2-11-BL-256",
    "location_id": "STO-TST",
    "on_hand": 14,
    "reserved": 8,
    "available": 6,
    "updated_at": "2025-10-06T10:11:54.647131Z"
  },
  {
    "variant_id": "V-IPAD-AIRM2-11-BL-512",
    "location_id": "WH-HK",
    "on_hand": 17,
    "reserved": 7,
    "available": 10,
    "updated_at": "2025-10-06T10:11:54.647135Z"
  },
  {
    "variant_id": "V-IPAD-AIRM2-11-BL-512",
    "location_id": "STO-CWB",
    "on_hand": 7,
    "reserved": 1,
    "available": 6,
    "updated_at": "2025-10-06T10:11:54.647138Z"
  },
  {
    "variant_id": "V-IPAD-AIRM2-11-BL-512",
    "location_id": "STO-TST",
    "on_hand": 14,
    "reserved": 8,
    "available": 6,
    "updated_at": "2025-10-06T10:11:54.647142Z"
  },
  {
    "variant_id": "V-IPAD-AIRM2-11-PU-128",
    "location_id": "WH-HK",
    "on_hand": 17,
    "reserved": 4,
    "available": 13,
    "updated_at": "2025-10-06T10:11:54.647146Z"
  },
  {
    "variant_id": "V-IPAD-AIRM2-11-PU-128",
    "location_id": "STO-CWB",
    "on_hand": 12,
    "reserved": 3,
    "available": 9,
    "updated_at": "2025-10-06T10:11:54.647150Z"
  },
  {
    "variant_id": "V-IPAD-AIRM2-11-PU-128",
    "location_id": "STO-TST",
    "on_hand": 6,
    "reserved": 0,
    "available": 6,
    "updated_at": "2025-10-06T10:11:54.647154Z"
  },
  {
    "variant_id": "V-IPAD-AIRM2-11-PU-256",
    "location_id": "WH-HK",
    "on_hand": 9,
    "reserved": 0,
    "available": 9,
    "updated_at": "2025-10-06T10:11:54.647157Z"
  },
  {
    "variant_id": "V-IPAD-AIRM2-11-PU-256",
    "location_id": "STO-CWB",
    "on_hand": 16,
    "reserved": 6,
    "available": 10,
    "updated_at": "2025-10-06T10:11:54.647161Z"
  },
  {
    "variant_id": "V-IPAD-AIRM2-11-PU-256",
    "location_id": "STO-TST",
    "on_hand": 16,
    "reserved": 3,
    "available": 13,
    "updated_at": "2025-10-06T10:11:54.647164Z"
  },
  {
    "variant_id": "V-IPAD-AIRM2-11-PU-512",
    "location_id": "WH-HK",
    "on_hand": 1,
    "reserved": 1,
    "available": 0,
    "updated_at": "2025-10-06T10:11:54.647168Z"
  },
  {
    "variant_id": "V-IPAD-AIRM2-11-PU-512",
    "location_id": "STO-CWB",
    "on_hand": 14,
    "reserved": 6,
    "available": 8,
    "updated_at": "2025-10-06T10:11:54.647172Z"
  },
  {
    "variant_id": "V-IPAD-AIRM2-11-PU-512",
    "location_id": "STO-TST",
    "on_hand": 17,
    "reserved": 6,
    "available": 11,
    "updated_at": "2025-10-06T10:11:54.647176Z"
  },
  {
    "variant_id": "V-IPAD-AIRM2-11-ST-128",
    "location_id": "WH-HK",
    "on_hand": 15,
    "reserved": 3,
    "available": 12,
    "updated_at": "2025-10-06T10:11:54.647179Z"
  },
  {
    "variant_id": "V-IPAD-AIRM2-11-ST-128",
    "location_id": "STO-CWB",
    "on_hand": 0,
    "reserved": 0,
    "available": 0,
    "updated_at": "2025-10-06T10:11:54.647183Z"
  },
  {
    "variant_id": "V-IPAD-AIRM2-11-ST-128",
    "location_id": "STO-TST",
    "on_hand": 7,
    "reserved": 0,
    "available": 7,
    "updated_at": "2025-10-06T10:11:54.647187Z"
  },
  {
    "variant_id": "V-IPAD-AIRM2-11-ST-256",
    "location_id": "WH-HK",
    "on_hand": 5,
    "reserved": 3,
    "available": 2,
    "updated_at": "2025-10-06T10:11:54.647191Z"
  },
  {
    "variant_id": "V-IPAD-AIRM2-11-ST-256",
    "location_id": "STO-CWB",
    "on_hand": 7,
    "reserved": 2,
    "available": 5,
    "updated_at": "2025-10-06T10:11:54.647194Z"
  },
  {
    "variant_id": "V-IPAD-AIRM2-11-ST-256",
    "location_id": "STO-TST",
    "on_hand": 21,
    "reserved": 5,
    "available": 16,
    "updated_at": "2025-10-06T10:11:54.647198Z"
  },
  {
    "variant_id": "V-IPAD-AIRM2-11-ST-512",
    "location_id": "WH-HK",
    "on_hand": 0,
    "reserved": 0,
    "available": 0,
    "updated_at": "2025-10-06T10:11:54.647202Z"
  },
  {
    "variant_id": "V-IPAD-AIRM2-11-ST-512",
    "location_id": "STO-CWB",
    "on_hand": 19,
    "reserved": 4,
    "available": 15,
    "updated_at": "2025-10-06T10:11:54.647206Z"
  },
  {
    "variant_id": "V-IPAD-AIRM2-11-ST-512",
    "location_id": "STO-TST",
    "on_hand": 6,
    "reserved": 4,
    "available": 2,
    "updated_at": "2025-10-06T10:11:54.647209Z"
  },
  {
    "variant_id": "V-IPAD-AIRM2-11-SP-128",
    "location_id": "WH-HK",
    "on_hand": 2,
    "reserved": 2,
    "available": 0,
    "updated_at": "2025-10-06T10:11:54.647213Z"
  },
  {
    "variant_id": "V-IPAD-AIRM2-11-SP-128",
    "location_id": "STO-CWB",
    "on_hand": 18,
    "reserved": 4,
    "available": 14,
    "updated_at": "2025-10-06T10:11:54.647217Z"
  },
  {
    "variant_id": "V-IPAD-AIRM2-11-SP-128",
    "location_id": "STO-TST",
    "on_hand": 24,
    "reserved": 4,
    "available": 20,
    "updated_at": "2025-10-06T10:11:54.647221Z"
  },
  {
    "variant_id": "V-IPAD-AIRM2-11-SP-256",
    "location_id": "WH-HK",
    "on_hand": 18,
    "reserved": 0,
    "available": 18,
    "updated_at": "2025-10-06T10:11:54.647225Z"
  },
  {
    "variant_id": "V-IPAD-AIRM2-11-SP-256",
    "location_id": "STO-CWB",
    "on_hand": 12,
    "reserved": 7,
    "available": 5,
    "updated_at": "2025-10-06T10:11:54.647228Z"
  },
  {
    "variant_id": "V-IPAD-AIRM2-11-SP-256",
    "location_id": "STO-TST",
    "on_hand": 19,
    "reserved": 8,
    "available": 11,
    "updated_at": "2025-10-06T10:11:54.647232Z"
  },
  {
    "variant_id": "V-IPAD-AIRM2-11-SP-512",
    "location_id": "WH-HK",
    "on_hand": 20,
    "reserved": 3,
    "available": 17,
    "updated_at": "2025-10-06T10:11:54.647236Z"
  },
  {
    "variant_id": "V-IPAD-AIRM2-11-SP-512",
    "location_id": "STO-CWB",
    "on_hand": 1,
    "reserved": 0,
    "available": 1,
    "updated_at": "2025-10-06T10:11:54.647240Z"
  },
  {
    "variant_id": "V-IPAD-AIRM2-11-SP-512",
    "location_id": "STO-TST",
    "on_hand": 3,
    "reserved": 3,
    "available": 0,
    "updated_at": "2025-10-06T10:11:54.647243Z"
  },
  {
    "variant_id": "V-MBA13-M3-MI-8-256",
    "location_id": "WH-HK",
    "on_hand": 12,
    "reserved": 2,
    "available": 10,
    "updated_at": "2025-10-06T10:11:54.647247Z"
  },
  {
    "variant_id": "V-MBA13-M3-MI-8-256",
    "location_id": "STO-CWB",
    "on_hand": 15,
    "reserved": 4,
    "available": 11,
    "updated_at": "2025-10-06T10:11:54.647251Z"
  },
  {
    "variant_id": "V-MBA13-M3-MI-8-256",
    "location_id": "STO-TST",
    "on_hand": 22,
    "reserved": 3,
    "available": 19,
    "updated_at": "2025-10-06T10:11:54.647254Z"
  },
  {
    "variant_id": "V-MBA13-M3-MI-8-512",
    "location_id": "WH-HK",
    "on_hand": 10,
    "reserved": 6,
    "available": 4,
    "updated_at": "2025-10-06T10:11:54.647258Z"
  },
  {
    "variant_id": "V-MBA13-M3-MI-8-512",
    "location_id": "STO-CWB",
    "on_hand": 0,
    "reserved": 0,
    "available": 0,
    "updated_at": "2025-10-06T10:11:54.647262Z"
  },
  {
    "variant_id": "V-MBA13-M3-MI-8-512",
    "location_id": "STO-TST",
    "on_hand": 7,
    "reserved": 3,
    "available": 4,
    "updated_at": "2025-10-06T10:11:54.647265Z"
  },
  {
    "variant_id": "V-MBA13-M3-MI-8-1024",
    "location_id": "WH-HK",
    "on_hand": 14,
    "reserved": 7,
    "available": 7,
    "updated_at": "2025-10-06T10:11:54.647269Z"
  },
  {
    "variant_id": "V-MBA13-M3-MI-8-1024",
    "location_id": "STO-CWB",
    "on_hand": 22,
    "reserved": 1,
    "available": 21,
    "updated_at": "2025-10-06T10:11:54.647272Z"
  },
  {
    "variant_id": "V-MBA13-M3-MI-8-1024",
    "location_id": "STO-TST",
    "on_hand": 12,
    "reserved": 8,
    "available": 4,
    "updated_at": "2025-10-06T10:11:54.647276Z"
  },
  {
    "variant_id": "V-MBA13-M3-MI-16-256",
    "location_id": "WH-HK",
    "on_hand": 21,
    "reserved": 4,
    "available": 17,
    "updated_at": "2025-10-06T10:11:54.647279Z"
  },
  {
    "variant_id": "V-MBA13-M3-MI-16-256",
    "location_id": "STO-CWB",
    "on_hand": 1,
    "reserved": 0,
    "available": 1,
    "updated_at": "2025-10-06T10:11:54.647299Z"
  },
  {
    "variant_id": "V-MBA13-M3-MI-16-256",
    "location_id": "STO-TST",
    "on_hand": 9,
    "reserved": 1,
    "available": 8,
    "updated_at": "2025-10-06T10:11:54.647302Z"
  },
  {
    "variant_id": "V-MBA13-M3-MI-16-512",
    "location_id": "WH-HK",
    "on_hand": 13,
    "reserved": 8,
    "available": 5,
    "updated_at": "2025-10-06T10:11:54.647306Z"
  },
  {
    "variant_id": "V-MBA13-M3-MI-16-512",
    "location_id": "STO-CWB",
    "on_hand": 21,
    "reserved": 8,
    "available": 13,
    "updated_at": "2025-10-06T10:11:54.647310Z"
  },
  {
    "variant_id": "V-MBA13-M3-MI-16-512",
    "location_id": "STO-TST",
    "on_hand": 11,
    "reserved": 0,
    "available": 11,
    "updated_at": "2025-10-06T10:11:54.647313Z"
  },
  {
    "variant_id": "V-MBA13-M3-MI-16-1024",
    "location_id": "WH-HK",
    "on_hand": 3,
    "reserved": 2,
    "available": 1,
    "updated_at": "2025-10-06T10:11:54.647317Z"
  },
  {
    "variant_id": "V-MBA13-M3-MI-16-1024",
    "location_id": "STO-CWB",
    "on_hand": 13,
    "reserved": 4,
    "available": 9,
    "updated_at": "2025-10-06T10:11:54.647320Z"
  },
  {
    "variant_id": "V-MBA13-M3-MI-16-1024",
    "location_id": "STO-TST",
    "on_hand": 6,
    "reserved": 4,
    "available": 2,
    "updated_at": "2025-10-06T10:11:54.647323Z"
  },
  {
    "variant_id": "V-MBA13-M3-ST-8-256",
    "location_id": "WH-HK",
    "on_hand": 2,
    "reserved": 1,
    "available": 1,
    "updated_at": "2025-10-06T10:11:54.647327Z"
  },
  {
    "variant_id": "V-MBA13-M3-ST-8-256",
    "location_id": "STO-CWB",
    "on_hand": 23,
    "reserved": 7,
    "available": 16,
    "updated_at": "2025-10-06T10:11:54.647330Z"
  },
  {
    "variant_id": "V-MBA13-M3-ST-8-256",
    "location_id": "STO-TST",
    "on_hand": 1,
    "reserved": 0,
    "available": 1,
    "updated_at": "2025-10-06T10:11:54.647336Z"
  },
  {
    "variant_id": "V-MBA13-M3-ST-8-512",
    "location_id": "WH-HK",
    "on_hand": 13,
    "reserved": 6,
    "available": 7,
    "updated_at": "2025-10-06T10:11:54.647355Z"
  },
  {
    "variant_id": "V-MBA13-M3-ST-8-512",
    "location_id": "STO-CWB",
    "on_hand": 21,
    "reserved": 0,
    "available": 21,
    "updated_at": "2025-10-06T10:11:54.647359Z"
  },
  {
    "variant_id": "V-MBA13-M3-ST-8-512",
    "location_id": "STO-TST",
    "on_hand": 12,
    "reserved": 2,
    "available": 10,
    "updated_at": "2025-10-06T10:11:54.647362Z"
  },
  {
    "variant_id": "V-MBA13-M3-ST-8-1024",
    "location_id": "WH-HK",
    "on_hand": 11,
    "reserved": 8,
    "available": 3,
    "updated_at": "2025-10-06T10:11:54.647365Z"
  },
  {
    "variant_id": "V-MBA13-M3-ST-8-1024",
    "location_id": "STO-CWB",
    "on_hand": 9,
    "reserved": 7,
    "available": 2,
    "updated_at": "2025-10-06T10:11:54.647369Z"
  },
  {
    "variant_id": "V-MBA13-M3-ST-8-1024",
    "location_id": "STO-TST",
    "on_hand": 9,
    "reserved": 4,
    "available": 5,
    "updated_at": "2025-10-06T10:11:54.647372Z"
  },
  {
    "variant_id": "V-MBA13-M3-ST-16-256",
    "location_id": "WH-HK",
    "on_hand": 10,
    "reserved": 4,
    "available": 6,
    "updated_at": "2025-10-06T10:11:54.647375Z"
  },
  {
    "variant_id": "V-MBA13-M3-ST-16-256",
    "location_id": "STO-CWB",
    "on_hand": 11,
    "reserved": 0,
    "available": 11,
    "updated_at": "2025-10-06T10:11:54.647379Z"
  },
  {
    "variant_id": "V-MBA13-M3-ST-16-256",
    "location_id": "STO-TST",
    "on_hand": 14,
    "reserved": 1,
    "available": 13,
    "updated_at": "2025-10-06T10:11:54.647382Z"
  },
  {
    "variant_id": "V-MBA13-M3-ST-16-512",
    "location_id": "WH-HK",
    "on_hand": 17,
    "reserved": 0,
    "available": 17,
    "updated_at": "2025-10-06T10:11:54.647386Z"
  },
  {
    "variant_id": "V-MBA13-M3-ST-16-512",
    "location_id": "STO-CWB",
    "on_hand": 11,
    "reserved": 4,
    "available": 7,
    "updated_at": "2025-10-06T10:11:54.647389Z"
  },
  {
    "variant_id": "V-MBA13-M3-ST-16-512",
    "location_id": "STO-TST",
    "on_hand": 5,
    "reserved": 0,
    "available": 5,
    "updated_at": "2025-10-06T10:11:54.647392Z"
  },
  {
    "variant_id": "V-MBA13-M3-ST-16-1024",
    "location_id": "WH-HK",
    "on_hand": 6,
    "reserved": 6,
    "available": 0,
    "updated_at": "2025-10-06T10:11:54.647396Z"
  },
  {
    "variant_id": "V-MBA13-M3-ST-16-1024",
    "location_id": "STO-CWB",
    "on_hand": 17,
    "reserved": 3,
    "available": 14,
    "updated_at": "2025-10-06T10:11:54.647399Z"
  },
  {
    "variant_id": "V-MBA13-M3-ST-16-1024",
    "location_id": "STO-TST",
    "on_hand": 15,
    "reserved": 1,
    "available": 14,
    "updated_at": "2025-10-06T10:11:54.647402Z"
  },
  {
    "variant_id": "V-MBA13-M3-SI-8-256",
    "location_id": "WH-HK",
    "on_hand": 15,
    "reserved": 2,
    "available": 13,
    "updated_at": "2025-10-06T10:11:54.647405Z"
  },
  {
    "variant_id": "V-MBA13-M3-SI-8-256",
    "location_id": "STO-CWB",
    "on_hand": 15,
    "reserved": 3,
    "available": 12,
    "updated_at": "2025-10-06T10:11:54.647409Z"
  },
  {
    "variant_id": "V-MBA13-M3-SI-8-256",
    "location_id": "STO-TST",
    "on_hand": 3,
    "reserved": 2,
    "available": 1,
    "updated_at": "2025-10-06T10:11:54.647412Z"
  },
  {
    "variant_id": "V-MBA13-M3-SI-8-512",
    "location_id": "WH-HK",
    "on_hand": 10,
    "reserved": 2,
    "available": 8,
    "updated_at": "2025-10-06T10:11:54.647415Z"
  },
  {
    "variant_id": "V-MBA13-M3-SI-8-512",
    "location_id": "STO-CWB",
    "on_hand": 5,
    "reserved": 0,
    "available": 5,
    "updated_at": "2025-10-06T10:11:54.647418Z"
  },
  {
    "variant_id": "V-MBA13-M3-SI-8-512",
    "location_id": "STO-TST",
    "on_hand": 16,
    "reserved": 8,
    "available": 8,
    "updated_at": "2025-10-06T10:11:54.647422Z"
  },
  {
    "variant_id": "V-MBA13-M3-SI-8-1024",
    "location_id": "WH-HK",
    "on_hand": 12,
    "reserved": 2,
    "available": 10,
    "updated_at": "2025-10-06T10:11:54.647425Z"
  },
  {
    "variant_id": "V-MBA13-M3-SI-8-1024",
    "location_id": "STO-CWB",
    "on_hand": 5,
    "reserved": 3,
    "available": 2,
    "updated_at": "2025-10-06T10:11:54.647428Z"
  },
  {
    "variant_id": "V-MBA13-M3-SI-8-1024",
    "location_id": "STO-TST",
    "on_hand": 19,
    "reserved": 4,
    "available": 15,
    "updated_at": "2025-10-06T10:11:54.647433Z"
  },
  {
    "variant_id": "V-MBA13-M3-SI-16-256",
    "location_id": "WH-HK",
    "on_hand": 0,
    "reserved": 0,
    "available": 0,
    "updated_at": "2025-10-06T10:11:54.647437Z"
  },
  {
    "variant_id": "V-MBA13-M3-SI-16-256",
    "location_id": "STO-CWB",
    "on_hand": 6,
    "reserved": 5,
    "available": 1,
    "updated_at": "2025-10-06T10:11:54.647441Z"
  },
  {
    "variant_id": "V-MBA13-M3-SI-16-256",
    "location_id": "STO-TST",
    "on_hand": 0,
    "reserved": 0,
    "available": 0,
    "updated_at": "2025-10-06T10:11:54.647460Z"
  },
  {
    "variant_id": "V-MBA13-M3-SI-16-512",
    "location_id": "WH-HK",
    "on_hand": 13,
    "reserved": 3,
    "available": 10,
    "updated_at": "2025-10-06T10:11:54.647464Z"
  },
  {
    "variant_id": "V-MBA13-M3-SI-16-512",
    "location_id": "STO-CWB",
    "on_hand": 22,
    "reserved": 0,
    "available": 22,
    "updated_at": "2025-10-06T10:11:54.647467Z"
  },
  {
    "variant_id": "V-MBA13-M3-SI-16-512",
    "location_id": "STO-TST",
    "on_hand": 10,
    "reserved": 0,
    "available": 10,
    "updated_at": "2025-10-06T10:11:54.647470Z"
  },
  {
    "variant_id": "V-MBA13-M3-SI-16-1024",
    "location_id": "WH-HK",
    "on_hand": 25,
    "reserved": 5,
    "available": 20,
    "updated_at": "2025-10-06T10:11:54.647497Z"
  },
  {
    "variant_id": "V-MBA13-M3-SI-16-1024",
    "location_id": "STO-CWB",
    "on_hand": 20,
    "reserved": 6,
    "available": 14,
    "updated_at": "2025-10-06T10:11:54.647501Z"
  },
  {
    "variant_id": "V-MBA13-M3-SI-16-1024",
    "location_id": "STO-TST",
    "on_hand": 15,
    "reserved": 4,
    "available": 11,
    "updated_at": "2025-10-06T10:11:54.647504Z"
  },
  {
    "variant_id": "V-MBA13-M3-SP-8-256",
    "location_id": "WH-HK",
    "on_hand": 17,
    "reserved": 4,
    "available": 13,
    "updated_at": "2025-10-06T10:11:54.647509Z"
  },
  {
    "variant_id": "V-MBA13-M3-SP-8-256",
    "location_id": "STO-CWB",
    "on_hand": 17,
    "reserved": 5,
    "available": 12,
    "updated_at": "2025-10-06T10:11:54.647512Z"
  },
  {
    "variant_id": "V-MBA13-M3-SP-8-256",
    "location_id": "STO-TST",
    "on_hand": 9,
    "reserved": 6,
    "available": 3,
    "updated_at": "2025-10-06T10:11:54.647531Z"
  },
  {
    "variant_id": "V-MBA13-M3-SP-8-512",
    "location_id": "WH-HK",
    "on_hand": 0,
    "reserved": 0,
    "available": 0,
    "updated_at": "2025-10-06T10:11:54.647535Z"
  },
  {
    "variant_id": "V-MBA13-M3-SP-8-512",
    "location_id": "STO-CWB",
    "on_hand": 25,
    "reserved": 5,
    "available": 20,
    "updated_at": "2025-10-06T10:11:54.647538Z"
  },
  {
    "variant_id": "V-MBA13-M3-SP-8-512",
    "location_id": "STO-TST",
    "on_hand": 2,
    "reserved": 1,
    "available": 1,
    "updated_at": "2025-10-06T10:11:54.647541Z"
  },
  {
    "variant_id": "V-MBA13-M3-SP-8-1024",
    "location_id": "WH-HK",
    "on_hand": 1,
    "reserved": 0,
    "available": 1,
    "updated_at": "2025-10-06T10:11:54.647544Z"
  },
  {
    "variant_id": "V-MBA13-M3-SP-8-1024",
    "location_id": "STO-CWB",
    "on_hand": 16,
    "reserved": 3,
    "available": 13,
    "updated_at": "2025-10-06T10:11:54.647547Z"
  },
  {
    "variant_id": "V-MBA13-M3-SP-8-1024",
    "location_id": "STO-TST",
    "on_hand": 19,
    "reserved": 4,
    "available": 15,
    "updated_at": "2025-10-06T10:11:54.647567Z"
  },
  {
    "variant_id": "V-MBA13-M3-SP-16-256",
    "location_id": "WH-HK",
    "on_hand": 19,
    "reserved": 4,
    "available": 15,
    "updated_at": "2025-10-06T10:11:54.647571Z"
  },
  {
    "variant_id": "V-MBA13-M3-SP-16-256",
    "location_id": "STO-CWB",
    "on_hand": 2,
    "reserved": 0,
    "available": 2,
    "updated_at": "2025-10-06T10:11:54.647574Z"
  },
  {
    "variant_id": "V-MBA13-M3-SP-16-256",
    "location_id": "STO-TST",
    "on_hand": 6,
    "reserved": 0,
    "available": 6,
    "updated_at": "2025-10-06T10:11:54.647578Z"
  },
  {
    "variant_id": "V-MBA13-M3-SP-16-512",
    "location_id": "WH-HK",
    "on_hand": 8,
    "reserved": 2,
    "available": 6,
    "updated_at": "2025-10-06T10:11:54.647581Z"
  },
  {
    "variant_id": "V-MBA13-M3-SP-16-512",
    "location_id": "STO-CWB",
    "on_hand": 19,
    "reserved": 3,
    "available": 16,
    "updated_at": "2025-10-06T10:11:54.647584Z"
  },
  {
    "variant_id": "V-MBA13-M3-SP-16-512",
    "location_id": "STO-TST",
    "on_hand": 17,
    "reserved": 3,
    "available": 14,
    "updated_at": "2025-10-06T10:11:54.647587Z"
  },
  {
    "variant_id": "V-MBA13-M3-SP-16-1024",
    "location_id": "WH-HK",
    "on_hand": 20,
    "reserved": 2,
    "available": 18,
    "updated_at": "2025-10-06T10:11:54.647591Z"
  },
  {
    "variant_id": "V-MBA13-M3-SP-16-1024",
    "location_id": "STO-CWB",
    "on_hand": 18,
    "reserved": 8,
    "available": 10,
    "updated_at": "2025-10-06T10:11:54.647594Z"
  },
  {
    "variant_id": "V-MBA13-M3-SP-16-1024",
    "location_id": "STO-TST",
    "on_hand": 4,
    "reserved": 3,
    "available": 1,
    "updated_at": "2025-10-06T10:11:54.647597Z"
  },
  {
    "variant_id": "V-MBP14-M3PRO-SI-18-512",
    "location_id": "WH-HK",
    "on_hand": 4,
    "reserved": 0,
    "available": 4,
    "updated_at": "2025-10-06T10:11:54.647601Z"
  },
  {
    "variant_id": "V-MBP14-M3PRO-SI-18-512",
    "location_id": "STO-CWB",
    "on_hand": 15,
    "reserved": 3,
    "available": 12,
    "updated_at": "2025-10-06T10:11:54.647604Z"
  },
  {
    "variant_id": "V-MBP14-M3PRO-SI-18-512",
    "location_id": "STO-TST",
    "on_hand": 19,
    "reserved": 7,
    "available": 12,
    "updated_at": "2025-10-06T10:11:54.647607Z"
  },
  {
    "variant_id": "V-MBP14-M3PRO-SI-18-1024",
    "location_id": "WH-HK",
    "on_hand": 11,
    "reserved": 0,
    "available": 11,
    "updated_at": "2025-10-06T10:11:54.647611Z"
  },
  {
    "variant_id": "V-MBP14-M3PRO-SI-18-1024",
    "location_id": "STO-CWB",
    "on_hand": 14,
    "reserved": 7,
    "available": 7,
    "updated_at": "2025-10-06T10:11:54.647614Z"
  },
  {
    "variant_id": "V-MBP14-M3PRO-SI-18-1024",
    "location_id": "STO-TST",
    "on_hand": 8,
    "reserved": 5,
    "available": 3,
    "updated_at": "2025-10-06T10:11:54.647617Z"
  },
  {
    "variant_id": "V-MBP14-M3PRO-SI-18-2048",
    "location_id": "WH-HK",
    "on_hand": 11,
    "reserved": 0,
    "available": 11,
    "updated_at": "2025-10-06T10:11:54.647620Z"
  },
  {
    "variant_id": "V-MBP14-M3PRO-SI-18-2048",
    "location_id": "STO-CWB",
    "on_hand": 13,
    "reserved": 1,
    "available": 12,
    "updated_at": "2025-10-06T10:11:54.647624Z"
  },
  {
    "variant_id": "V-MBP14-M3PRO-SI-18-2048",
    "location_id": "STO-TST",
    "on_hand": 11,
    "reserved": 8,
    "available": 3,
    "updated_at": "2025-10-06T10:11:54.647627Z"
  },
  {
    "variant_id": "V-MBP14-M3PRO-SI-36-512",
    "location_id": "WH-HK",
    "on_hand": 6,
    "reserved": 3,
    "available": 3,
    "updated_at": "2025-10-06T10:11:54.647632Z"
  },
  {
    "variant_id": "V-MBP14-M3PRO-SI-36-512",
    "location_id": "STO-CWB",
    "on_hand": 4,
    "reserved": 1,
    "available": 3,
    "updated_at": "2025-10-06T10:11:54.647651Z"
  },
  {
    "variant_id": "V-MBP14-M3PRO-SI-36-512",
    "location_id": "STO-TST",
    "on_hand": 7,
    "reserved": 0,
    "available": 7,
    "updated_at": "2025-10-06T10:11:54.647655Z"
  },
  {
    "variant_id": "V-MBP14-M3PRO-SI-36-1024",
    "location_id": "WH-HK",
    "on_hand": 4,
    "reserved": 2,
    "available": 2,
    "updated_at": "2025-10-06T10:11:54.647658Z"
  },
  {
    "variant_id": "V-MBP14-M3PRO-SI-36-1024",
    "location_id": "STO-CWB",
    "on_hand": 15,
    "reserved": 5,
    "available": 10,
    "updated_at": "2025-10-06T10:11:54.647661Z"
  },
  {
    "variant_id": "V-MBP14-M3PRO-SI-36-1024",
    "location_id": "STO-TST",
    "on_hand": 9,
    "reserved": 2,
    "available": 7,
    "updated_at": "2025-10-06T10:11:54.647664Z"
  },
  {
    "variant_id": "V-MBP14-M3PRO-SI-36-2048",
    "location_id": "WH-HK",
    "on_hand": 3,
    "reserved": 2,
    "available": 1,
    "updated_at": "2025-10-06T10:11:54.647667Z"
  },
  {
    "variant_id": "V-MBP14-M3PRO-SI-36-2048",
    "location_id": "STO-CWB",
    "on_hand": 6,
    "reserved": 1,
    "available": 5,
    "updated_at": "2025-10-06T10:11:54.647671Z"
  },
  {
    "variant_id": "V-MBP14-M3PRO-SI-36-2048",
    "location_id": "STO-TST",
    "on_hand": 19,
    "reserved": 1,
    "available": 18,
    "updated_at": "2025-10-06T10:11:54.647674Z"
  },
  {
    "variant_id": "V-MBP14-M3PRO-SP-18-512",
    "location_id": "WH-HK",
    "on_hand": 8,
    "reserved": 8,
    "available": 0,
    "updated_at": "2025-10-06T10:11:54.647677Z"
  },
  {
    "variant_id": "V-MBP14-M3PRO-SP-18-512",
    "location_id": "STO-CWB",
    "on_hand": 15,
    "reserved": 0,
    "available": 15,
    "updated_at": "2025-10-06T10:11:54.647680Z"
  },
  {
    "variant_id": "V-MBP14-M3PRO-SP-18-512",
    "location_id": "STO-TST",
    "on_hand": 8,
    "reserved": 2,
    "available": 6,
    "updated_at": "2025-10-06T10:11:54.647684Z"
  },
  {
    "variant_id": "V-MBP14-M3PRO-SP-18-1024",
    "location_id": "WH-HK",
    "on_hand": 13,
    "reserved": 7,
    "available": 6,
    "updated_at": "2025-10-06T10:11:54.647687Z"
  },
  {
    "variant_id": "V-MBP14-M3PRO-SP-18-1024",
    "location_id": "STO-CWB",
    "on_hand": 6,
    "reserved": 2,
    "available": 4,
    "updated_at": "2025-10-06T10:11:54.647690Z"
  },
  {
    "variant_id": "V-MBP14-M3PRO-SP-18-1024",
    "location_id": "STO-TST",
    "on_hand": 10,
    "reserved": 1,
    "available": 9,
    "updated_at": "2025-10-06T10:11:54.647693Z"
  },
  {
    "variant_id": "V-MBP14-M3PRO-SP-18-2048",
    "location_id": "WH-HK",
    "on_hand": 9,
    "reserved": 3,
    "available": 6,
    "updated_at": "2025-10-06T10:11:54.647697Z"
  },
  {
    "variant_id": "V-MBP14-M3PRO-SP-18-2048",
    "location_id": "STO-CWB",
    "on_hand": 15,
    "reserved": 2,
    "available": 13,
    "updated_at": "2025-10-06T10:11:54.647700Z"
  },
  {
    "variant_id": "V-MBP14-M3PRO-SP-18-2048",
    "location_id": "STO-TST",
    "on_hand": 19,
    "reserved": 3,
    "available": 16,
    "updated_at": "2025-10-06T10:11:54.647703Z"
  },
  {
    "variant_id": "V-MBP14-M3PRO-SP-36-512",
    "location_id": "WH-HK",
    "on_hand": 16,
    "reserved": 3,
    "available": 13,
    "updated_at": "2025-10-06T10:11:54.647723Z"
  },
  {
    "variant_id": "V-MBP14-M3PRO-SP-36-512",
    "location_id": "STO-CWB",
    "on_hand": 18,
    "reserved": 7,
    "available": 11,
    "updated_at": "2025-10-06T10:11:54.647726Z"
  },
  {
    "variant_id": "V-MBP14-M3PRO-SP-36-512",
    "location_id": "STO-TST",
    "on_hand": 8,
    "reserved": 7,
    "available": 1,
    "updated_at": "2025-10-06T10:11:54.647729Z"
  },
  {
    "variant_id": "V-MBP14-M3PRO-SP-36-1024",
    "location_id": "WH-HK",
    "on_hand": 0,
    "reserved": 0,
    "available": 0,
    "updated_at": "2025-10-06T10:11:54.647732Z"
  },
  {
    "variant_id": "V-MBP14-M3PRO-SP-36-1024",
    "location_id": "STO-CWB",
    "on_hand": 25,
    "reserved": 4,
    "available": 21,
    "updated_at": "2025-10-06T10:11:54.647753Z"
  },
  {
    "variant_id": "V-MBP14-M3PRO-SP-36-1024",
    "location_id": "STO-TST",
    "on_hand": 5,
    "reserved": 2,
    "available": 3,
    "updated_at": "2025-10-06T10:11:54.647768Z"
  },
  {
    "variant_id": "V-MBP14-M3PRO-SP-36-2048",
    "location_id": "WH-HK",
    "on_hand": 6,
    "reserved": 2,
    "available": 4,
    "updated_at": "2025-10-06T10:11:54.647772Z"
  },
  {
    "variant_id": "V-MBP14-M3PRO-SP-36-2048",
    "location_id": "STO-CWB",
    "on_hand": 14,
    "reserved": 2,
    "available": 12,
    "updated_at": "2025-10-06T10:11:54.647775Z"
  },
  {
    "variant_id": "V-MBP14-M3PRO-SP-36-2048",
    "location_id": "STO-TST",
    "on_hand": 12,
    "reserved": 3,
    "available": 9,
    "updated_at": "2025-10-06T10:11:54.647778Z"
  },
  {
    "variant_id": "V-AW-S9-41-MI-GPS",
    "location_id": "WH-HK",
    "on_hand": 24,
    "reserved": 6,
    "available": 18,
    "updated_at": "2025-10-06T10:11:54.647782Z"
  },
  {
    "variant_id": "V-AW-S9-41-MI-GPS",
    "location_id": "STO-CWB",
    "on_hand": 10,
    "reserved": 4,
    "available": 6,
    "updated_at": "2025-10-06T10:11:54.647785Z"
  },
  {
    "variant_id": "V-AW-S9-41-MI-GPS",
    "location_id": "STO-TST",
    "on_hand": 1,
    "reserved": 1,
    "available": 0,
    "updated_at": "2025-10-06T10:11:54.647789Z"
  },
  {
    "variant_id": "V-AW-S9-41-MI-CEL",
    "location_id": "WH-HK",
    "on_hand": 5,
    "reserved": 0,
    "available": 5,
    "updated_at": "2025-10-06T10:11:54.647792Z"
  },
  {
    "variant_id": "V-AW-S9-41-MI-CEL",
    "location_id": "STO-CWB",
    "on_hand": 24,
    "reserved": 0,
    "available": 24,
    "updated_at": "2025-10-06T10:11:54.647795Z"
  },
  {
    "variant_id": "V-AW-S9-41-MI-CEL",
    "location_id": "STO-TST",
    "on_hand": 19,
    "reserved": 4,
    "available": 15,
    "updated_at": "2025-10-06T10:11:54.647799Z"
  },
  {
    "variant_id": "V-AW-S9-41-ST-GPS",
    "location_id": "WH-HK",
    "on_hand": 21,
    "reserved": 3,
    "available": 18,
    "updated_at": "2025-10-06T10:11:54.647802Z"
  },
  {
    "variant_id": "V-AW-S9-41-ST-GPS",
    "location_id": "STO-CWB",
    "on_hand": 18,
    "reserved": 2,
    "available": 16,
    "updated_at": "2025-10-06T10:11:54.647830Z"
  },
  {
    "variant_id": "V-AW-S9-41-ST-GPS",
    "location_id": "STO-TST",
    "on_hand": 16,
    "reserved": 6,
    "available": 10,
    "updated_at": "2025-10-06T10:11:54.647837Z"
  },
  {
    "variant_id": "V-AW-S9-41-ST-CEL",
    "location_id": "WH-HK",
    "on_hand": 20,
    "reserved": 0,
    "available": 20,
    "updated_at": "2025-10-06T10:11:54.647860Z"
  },
  {
    "variant_id": "V-AW-S9-41-ST-CEL",
    "location_id": "STO-CWB",
    "on_hand": 14,
    "reserved": 6,
    "available": 8,
    "updated_at": "2025-10-06T10:11:54.647867Z"
  },
  {
    "variant_id": "V-AW-S9-41-ST-CEL",
    "location_id": "STO-TST",
    "on_hand": 24,
    "reserved": 7,
    "available": 17,
    "updated_at": "2025-10-06T10:11:54.647874Z"
  },
  {
    "variant_id": "V-AW-S9-41-SI-GPS",
    "location_id": "WH-HK",
    "on_hand": 6,
    "reserved": 4,
    "available": 2,
    "updated_at": "2025-10-06T10:11:54.647897Z"
  },
  {
    "variant_id": "V-AW-S9-41-SI-GPS",
    "location_id": "STO-CWB",
    "on_hand": 0,
    "reserved": 0,
    "available": 0,
    "updated_at": "2025-10-06T10:11:54.647904Z"
  },
  {
    "variant_id": "V-AW-S9-41-SI-GPS",
    "location_id": "STO-TST",
    "on_hand": 18,
    "reserved": 8,
    "available": 10,
    "updated_at": "2025-10-06T10:11:54.647911Z"
  },
  {
    "variant_id": "V-AW-S9-41-SI-CEL",
    "location_id": "WH-HK",
    "on_hand": 13,
    "reserved": 4,
    "available": 9,
    "updated_at": "2025-10-06T10:11:54.647918Z"
  },
  {
    "variant_id": "V-AW-S9-41-SI-CEL",
    "location_id": "STO-CWB",
    "on_hand": 17,
    "reserved": 8,
    "available": 9,
    "updated_at": "2025-10-06T10:11:54.647932Z"
  },
  {
    "variant_id": "V-AW-S9-41-SI-CEL",
    "location_id": "STO-TST",
    "on_hand": 4,
    "reserved": 3,
    "available": 1,
    "updated_at": "2025-10-06T10:11:54.647936Z"
  },
  {
    "variant_id": "V-AW-S9-41-(P-GPS",
    "location_id": "WH-HK",
    "on_hand": 10,
    "reserved": 3,
    "available": 7,
    "updated_at": "2025-10-06T10:11:54.647940Z"
  },
  {
    "variant_id": "V-AW-S9-41-(P-GPS",
    "location_id": "STO-CWB",
    "on_hand": 17,
    "reserved": 0,
    "available": 17,
    "updated_at": "2025-10-06T10:11:54.647944Z"
  },
  {
    "variant_id": "V-AW-S9-41-(P-GPS",
    "location_id": "STO-TST",
    "on_hand": 18,
    "reserved": 7,
    "available": 11,
    "updated_at": "2025-10-06T10:11:54.647947Z"
  },
  {
    "variant_id": "V-AW-S9-41-(P-CEL",
    "location_id": "WH-HK",
    "on_hand": 24,
    "reserved": 4,
    "available": 20,
    "updated_at": "2025-10-06T10:11:54.647952Z"
  },
  {
    "variant_id": "V-AW-S9-41-(P-CEL",
    "location_id": "STO-CWB",
    "on_hand": 15,
    "reserved": 0,
    "available": 15,
    "updated_at": "2025-10-06T10:11:54.647956Z"
  },
  {
    "variant_id": "V-AW-S9-41-(P-CEL",
    "location_id": "STO-TST",
    "on_hand": 13,
    "reserved": 4,
    "available": 9,
    "updated_at": "2025-10-06T10:11:54.647959Z"
  },
  {
    "variant_id": "V-AW-S9-45-MI-GPS",
    "location_id": "WH-HK",
    "on_hand": 4,
    "reserved": 3,
    "available": 1,
    "updated_at": "2025-10-06T10:11:54.647963Z"
  },
  {
    "variant_id": "V-AW-S9-45-MI-GPS",
    "location_id": "STO-CWB",
    "on_hand": 13,
    "reserved": 7,
    "available": 6,
    "updated_at": "2025-10-06T10:11:54.647967Z"
  },
  {
    "variant_id": "V-AW-S9-45-MI-GPS",
    "location_id": "STO-TST",
    "on_hand": 19,
    "reserved": 2,
    "available": 17,
    "updated_at": "2025-10-06T10:11:54.647970Z"
  },
  {
    "variant_id": "V-AW-S9-45-MI-CEL",
    "location_id": "WH-HK",
    "on_hand": 17,
    "reserved": 4,
    "available": 13,
    "updated_at": "2025-10-06T10:11:54.647974Z"
  },
  {
    "variant_id": "V-AW-S9-45-MI-CEL",
    "location_id": "STO-CWB",
    "on_hand": 12,
    "reserved": 8,
    "available": 4,
    "updated_at": "2025-10-06T10:11:54.647978Z"
  },
  {
    "variant_id": "V-AW-S9-45-MI-CEL",
    "location_id": "STO-TST",
    "on_hand": 16,
    "reserved": 8,
    "available": 8,
    "updated_at": "2025-10-06T10:11:54.647981Z"
  },
  {
    "variant_id": "V-AW-S9-45-ST-GPS",
    "location_id": "WH-HK",
    "on_hand": 9,
    "reserved": 0,
    "available": 9,
    "updated_at": "2025-10-06T10:11:54.647985Z"
  },
  {
    "variant_id": "V-AW-S9-45-ST-GPS",
    "location_id": "STO-CWB",
    "on_hand": 25,
    "reserved": 2,
    "available": 23,
    "updated_at": "2025-10-06T10:11:54.647989Z"
  },
  {
    "variant_id": "V-AW-S9-45-ST-GPS",
    "location_id": "STO-TST",
    "on_hand": 17,
    "reserved": 0,
    "available": 17,
    "updated_at": "2025-10-06T10:11:54.647994Z"
  },
  {
    "variant_id": "V-AW-S9-45-ST-CEL",
    "location_id": "WH-HK",
    "on_hand": 8,
    "reserved": 1,
    "available": 7,
    "updated_at": "2025-10-06T10:11:54.648000Z"
  },
  {
    "variant_id": "V-AW-S9-45-ST-CEL",
    "location_id": "STO-CWB",
    "on_hand": 10,
    "reserved": 8,
    "available": 2,
    "updated_at": "2025-10-06T10:11:54.648007Z"
  },
  {
    "variant_id": "V-AW-S9-45-ST-CEL",
    "location_id": "STO-TST",
    "on_hand": 23,
    "reserved": 2,
    "available": 21,
    "updated_at": "2025-10-06T10:11:54.648014Z"
  },
  {
    "variant_id": "V-AW-S9-45-SI-GPS",
    "location_id": "WH-HK",
    "on_hand": 4,
    "reserved": 0,
    "available": 4,
    "updated_at": "2025-10-06T10:11:54.648020Z"
  },
  {
    "variant_id": "V-AW-S9-45-SI-GPS",
    "location_id": "STO-CWB",
    "on_hand": 1,
    "reserved": 1,
    "available": 0,
    "updated_at": "2025-10-06T10:11:54.648027Z"
  },
  {
    "variant_id": "V-AW-S9-45-SI-GPS",
    "location_id": "STO-TST",
    "on_hand": 2,
    "reserved": 0,
    "available": 2,
    "updated_at": "2025-10-06T10:11:54.648033Z"
  },
  {
    "variant_id": "V-AW-S9-45-SI-CEL",
    "location_id": "WH-HK",
    "on_hand": 7,
    "reserved": 6,
    "available": 1,
    "updated_at": "2025-10-06T10:11:54.648040Z"
  },
  {
    "variant_id": "V-AW-S9-45-SI-CEL",
    "location_id": "STO-CWB",
    "on_hand": 3,
    "reserved": 3,
    "available": 0,
    "updated_at": "2025-10-06T10:11:54.648047Z"
  },
  {
    "variant_id": "V-AW-S9-45-SI-CEL",
    "location_id": "STO-TST",
    "on_hand": 23,
    "reserved": 8,
    "available": 15,
    "updated_at": "2025-10-06T10:11:54.648054Z"
  },
  {
    "variant_id": "V-AW-S9-45-(P-GPS",
    "location_id": "WH-HK",
    "on_hand": 25,
    "reserved": 4,
    "available": 21,
    "updated_at": "2025-10-06T10:11:54.648063Z"
  },
  {
    "variant_id": "V-AW-S9-45-(P-GPS",
    "location_id": "STO-CWB",
    "on_hand": 11,
    "reserved": 6,
    "available": 5,
    "updated_at": "2025-10-06T10:11:54.648068Z"
  },
  {
    "variant_id": "V-AW-S9-45-(P-GPS",
    "location_id": "STO-TST",
    "on_hand": 8,
    "reserved": 8,
    "available": 0,
    "updated_at": "2025-10-06T10:11:54.648071Z"
  },
  {
    "variant_id": "V-AW-S9-45-(P-CEL",
    "location_id": "WH-HK",
    "on_hand": 17,
    "reserved": 2,
    "available": 15,
    "updated_at": "2025-10-06T10:11:54.648075Z"
  },
  {
    "variant_id": "V-AW-S9-45-(P-CEL",
    "location_id": "STO-CWB",
    "on_hand": 2,
    "reserved": 0,
    "available": 2,
    "updated_at": "2025-10-06T10:11:54.648080Z"
  },
  {
    "variant_id": "V-AW-S9-45-(P-CEL",
    "location_id": "STO-TST",
    "on_hand": 17,
    "reserved": 0,
    "available": 17,
    "updated_at": "2025-10-06T10:11:54.648084Z"
  },
  {
    "variant_id": "V-AIRP2-USB-C",
    "location_id": "WH-HK",
    "on_hand": 18,
    "reserved": 3,
    "available": 15,
    "updated_at": "2025-10-06T10:11:54.648088Z"
  },
  {
    "variant_id": "V-AIRP2-USB-C",
    "location_id": "STO-CWB",
    "on_hand": 9,
    "reserved": 2,
    "available": 7,
    "updated_at": "2025-10-06T10:11:54.648091Z"
  },
  {
    "variant_id": "V-AIRP2-USB-C",
    "location_id": "STO-TST",
    "on_hand": 7,
    "reserved": 6,
    "available": 1,
    "updated_at": "2025-10-06T10:11:54.648095Z"
  }
]